{
    "Sources": [
        {
            "source": "2MASS J13595510-4034582",
            "ra_deg": 209.9796,
            "dec_deg": -40.5829,
            "epoch_year": 2000.0,
            "equinox": "J2000",
            "reference": "Reid08b",
            "other_references": null,
            "comments": null
        }
    ],
    "ModeledParameters": [
        {
            "model": "UCS adopted distance",
            "parameter": "distance",
            "value": 21.12,
            "error": 0.09,
            "error_upper": null,
            "error_lower": null,
            "unit": "pc",
            "comments": "distance source: dist_plx_formula",
            "reference": "UCS_24"
        },
        {
            "model": "UCS age assignment",
            "parameter": "age",
            "value": 0.135,
            "error": null,
            "error_upper": null,
            "error_lower": null,
            "unit": "Gyr",
            "comments": "age_category: beta; age range (Gyr): 0.02-0.25",
            "reference": "UCS_24"
        }
    ],
    "Names": [
        {
            "other_name": "2MASS J13595510-4034582"
        }
    ],
    "Parallaxes": [
        {
            "parallax_mas": 64.2,
            "parallax_error": 5.5,
            "parallax_error_upper": null,
            "parallax_error_lower": null,
            "adopted": false,
            "comments": null,
            "reference": "Fahe12"
        },
        {
            "parallax_mas": 47.346,
            "parallax_error": 0.2025,
            "parallax_error_upper": null,
            "parallax_error_lower": null,
            "adopted": false,
            "comments": null,
            "reference": "Gaia21a"
        },
        {
            "parallax_mas": 47.346,
            "parallax_error": 0.2025,
            "parallax_error_upper": null,
            "parallax_error_lower": null,
            "adopted": true,
            "comments": null,
            "reference": "Gaia23"
        }
    ],
    "Photometry": [
        {
            "band": "2MASS/2MASS.H",
            "magnitude": 13.034,
            "magnitude_error": 0.029,
            "magnitude_error_upper": null,
            "magnitude_error_lower": null,
            "telescope": "2MASS",
            "epoch": null,
            "comments": null,
            "reference": "Cutr03",
            "regime": "nir"
        },
        {
            "band": "2MASS/2MASS.J",
            "magnitude": 13.645,
            "magnitude_error": 0.026,
            "magnitude_error_upper": null,
            "magnitude_error_lower": null,
            "telescope": "2MASS",
            "epoch": null,
            "comments": null,
            "reference": "Cutr03",
            "regime": "nir"
        },
        {
            "band": "2MASS/2MASS.Ks",
            "magnitude": 12.566,
            "magnitude_error": 0.029,
            "magnitude_error_upper": null,
            "magnitude_error_lower": null,
            "telescope": "2MASS",
            "epoch": null,
            "comments": null,
            "reference": "Cutr03",
            "regime": "nir"
        },
        {
            "band": "GAIA/GAIA3.G",
            "magnitude": 18.4069,
            "magnitude_error": 0.0042,
            "magnitude_error_upper": null,
            "magnitude_error_lower": null,
            "telescope": "Gaia",
            "epoch": null,
            "comments": null,
            "reference": "Gaia23",
            "regime": "optical"
        },
        {
            "band": "GAIA/GAIA3.Gbp",
            "magnitude": 20.7879,
            "magnitude_error": 0.2348,
            "magnitude_error_upper": null,
            "magnitude_error_lower": null,
            "telescope": "Gaia",
            "epoch": null,
            "comments": null,
            "reference": "Gaia23",
            "regime": "optical"
        },
        {
            "band": "GAIA/GAIA3.Grp",
            "magnitude": 16.7962,
            "magnitude_error": 0.0139,
            "magnitude_error_upper": null,
            "magnitude_error_lower": null,
            "telescope": "Gaia",
            "epoch": null,
            "comments": null,
            "reference": "Gaia23",
            "regime": "optical"
        },
        {
            "band": "MKO/NSFCam.H",
            "magnitude": 13.06,
            "magnitude_error": 0.03,
            "magnitude_error_upper": null,
            "magnitude_error_lower": null,
            "telescope": null,
            "epoch": null,
            "comments": null,
            "reference": "Fahe12",
            "regime": "nir"
        },
        {
            "band": "MKO/NSFCam.J",
            "magnitude": 13.58,
            "magnitude_error": 0.03,
            "magnitude_error_upper": null,
            "magnitude_error_lower": null,
            "telescope": null,
            "epoch": null,
            "comments": null,
            "reference": "Fahe12",
            "regime": "nir"
        },
        {
            "band": "MKO/NSFCam.K",
            "magnitude": 12.54,
            "magnitude_error": 0.03,
            "magnitude_error_upper": null,
            "magnitude_error_lower": null,
            "telescope": null,
            "epoch": null,
            "comments": null,
            "reference": "Fahe12",
            "regime": "nir"
        },
        {
            "band": "UKIRT/WFCAM.Y",
            "magnitude": 14.588,
            "magnitude_error": 0.058,
            "magnitude_error_upper": null,
            "magnitude_error_lower": null,
            "telescope": null,
            "epoch": null,
            "comments": null,
            "reference": "Best21",
            "regime": "nir"
        },
        {
            "band": "WISE/WISE.W1",
            "magnitude": 12.211,
            "magnitude_error": 0.012,
            "magnitude_error_upper": null,
            "magnitude_error_lower": null,
            "telescope": "WISE",
            "epoch": null,
            "comments": null,
            "reference": "Maro21",
            "regime": "infrared"
        },
        {
            "band": "WISE/WISE.W2",
            "magnitude": 11.936,
            "magnitude_error": 0.008,
            "magnitude_error_upper": null,
            "magnitude_error_lower": null,
            "telescope": "WISE",
            "epoch": null,
            "comments": null,
            "reference": "Maro21",
            "regime": "infrared"
        },
        {
            "band": "WISE/WISE.W3",
            "magnitude": 11.35,
            "magnitude_error": 0.127,
            "magnitude_error_upper": null,
            "magnitude_error_lower": null,
            "telescope": "WISE",
            "epoch": null,
            "comments": null,
            "reference": "Cutr13",
            "regime": "infrared"
        },
        {
            "band": "WISE/WISE.W4",
            "magnitude": 9.449,
            "magnitude_error": null,
            "magnitude_error_upper": null,
            "magnitude_error_lower": null,
            "telescope": "WISE",
            "epoch": null,
            "comments": "upper limit",
            "reference": "Cutr13",
            "regime": "infrared"
        }
    ],
    "Positions": [
        {
            "ra_deg": 209.979603,
            "dec_deg": -40.582851,
            "epoch_year": 1999.2874743326488,
            "reference": "Cutr03"
        },
        {
            "ra_deg": 209.9796389,
            "dec_deg": -40.5829281,
            "epoch_year": 2000.0,
            "reference": "Gaia21a"
        },
        {
            "ra_deg": 209.9797974,
            "dec_deg": -40.5851784,
            "epoch_year": 2016.0,
            "reference": "Gaia23"
        },
        {
            "ra_deg": 209.9797769,
            "dec_deg": -40.5850696,
            "epoch_year": 2015.405,
            "reference": "Maro21"
        }
    ],
    "ProperMotions": [
        {
            "pm_ra": 64.6,
            "pm_ra_error": 7.7,
            "pm_ra_error_upper": null,
            "pm_ra_error_lower": null,
            "pm_dec": -494.1,
            "pm_dec_error": 6.7,
            "pm_dec_error_upper": null,
            "pm_dec_error_lower": null,
            "adopted": false,
            "comments": null,
            "reference": "Fahe12"
        },
        {
            "pm_ra": 26.978,
            "pm_ra_error": 0.251,
            "pm_ra_error_upper": null,
            "pm_ra_error_lower": null,
            "pm_dec": -505.994,
            "pm_dec_error": 0.269,
            "pm_dec_error_upper": null,
            "pm_dec_error_lower": null,
            "adopted": false,
            "comments": null,
            "reference": "Gaia21a"
        },
        {
            "pm_ra": 26.978,
            "pm_ra_error": 0.251,
            "pm_ra_error_upper": null,
            "pm_ra_error_lower": null,
            "pm_dec": -505.994,
            "pm_dec_error": 0.269,
            "pm_dec_error_upper": null,
            "pm_dec_error_lower": null,
            "adopted": true,
            "comments": null,
            "reference": "Gaia23"
        },
        {
            "pm_ra": 25.3,
            "pm_ra_error": 3.9,
            "pm_ra_error_upper": null,
            "pm_ra_error_lower": null,
            "pm_dec": -519.5,
            "pm_dec_error": 5.1,
            "pm_dec_error_upper": null,
            "pm_dec_error_lower": null,
            "adopted": false,
            "comments": null,
            "reference": "Maro21"
        }
    ],
    "SourceTypes": [
        {
            "source_type": "L1",
            "comments": "optical spectral type",
            "adopted": null,
            "reference": "Reid08b"
        },
        {
            "source_type": "L2 beta",
            "comments": "NIR spectral type",
            "adopted": null,
            "reference": "Bard19"
        }
    ]
}