{
    "Sources": [
        {
            "source": "SDSS J124510.86-013230.9",
            "ra_deg": 191.2952,
            "dec_deg": -1.5419,
            "epoch_year": 2000.0,
            "equinox": "J2000",
            "reference": "Schm10b",
            "other_references": null,
            "comments": null
        }
    ],
    "ModeledParameters": [
        {
            "model": "UCS adopted distance",
            "parameter": "distance",
            "value": 104.0,
            "error": 8.0,
            "error_upper": null,
            "error_lower": null,
            "unit": "pc",
            "comments": "distance source: dist_W2_formula",
            "reference": "UCS_24"
        },
        {
            "model": "UCS age assignment",
            "parameter": "age",
            "value": 2.5,
            "error": null,
            "error_upper": null,
            "error_lower": null,
            "unit": "Gyr",
            "comments": "age_category: Field; age range (Gyr): 2.5(+4.3/-2)",
            "reference": "UCS_24"
        }
    ],
    "Names": [
        {
            "other_name": "SDSS J124510.86-013230.9"
        }
    ],
    "Photometry": [
        {
            "band": "2MASS/2MASS.H",
            "magnitude": 16.081,
            "magnitude_error": 0.235,
            "magnitude_error_upper": null,
            "magnitude_error_lower": null,
            "telescope": "2MASS",
            "epoch": null,
            "comments": null,
            "reference": "Cutr03",
            "regime": "nir"
        },
        {
            "band": "2MASS/2MASS.J",
            "magnitude": 16.597,
            "magnitude_error": 0.14,
            "magnitude_error_upper": null,
            "magnitude_error_lower": null,
            "telescope": "2MASS",
            "epoch": null,
            "comments": null,
            "reference": "Cutr03",
            "regime": "nir"
        },
        {
            "band": "2MASS/2MASS.Ks",
            "magnitude": 15.609,
            "magnitude_error": 0.235,
            "magnitude_error_upper": null,
            "magnitude_error_lower": null,
            "telescope": "2MASS",
            "epoch": null,
            "comments": null,
            "reference": "Cutr03",
            "regime": "nir"
        },
        {
            "band": "GAIA/GAIA3.G",
            "magnitude": 21.2217,
            "magnitude_error": 0.0258,
            "magnitude_error_upper": null,
            "magnitude_error_lower": null,
            "telescope": "Gaia",
            "epoch": null,
            "comments": null,
            "reference": "Gaia23",
            "regime": "optical"
        },
        {
            "band": "GAIA/GAIA3.Grp",
            "magnitude": 19.5096,
            "magnitude_error": 0.1986,
            "magnitude_error_upper": null,
            "magnitude_error_lower": null,
            "telescope": "Gaia",
            "epoch": null,
            "comments": null,
            "reference": "Gaia23",
            "regime": "optical"
        },
        {
            "band": "MKO/NSFCam.H",
            "magnitude": 16.046,
            "magnitude_error": 0.018,
            "magnitude_error_upper": null,
            "magnitude_error_lower": null,
            "telescope": null,
            "epoch": null,
            "comments": null,
            "reference": "WFAU19",
            "regime": "nir"
        },
        {
            "band": "MKO/NSFCam.J",
            "magnitude": 16.639,
            "magnitude_error": 0.011,
            "magnitude_error_upper": null,
            "magnitude_error_lower": null,
            "telescope": null,
            "epoch": null,
            "comments": null,
            "reference": "WFAU19",
            "regime": "nir"
        },
        {
            "band": "MKO/NSFCam.K",
            "magnitude": 15.585,
            "magnitude_error": 0.018,
            "magnitude_error_upper": null,
            "magnitude_error_lower": null,
            "telescope": null,
            "epoch": null,
            "comments": null,
            "reference": "WFAU19",
            "regime": "nir"
        },
        {
            "band": "PAN-STARRS/PS1.i",
            "magnitude": 20.7796,
            "magnitude_error": 0.0337,
            "magnitude_error_upper": null,
            "magnitude_error_lower": null,
            "telescope": "PS1",
            "epoch": null,
            "comments": null,
            "reference": "Cham16",
            "regime": "optical"
        },
        {
            "band": "PAN-STARRS/PS1.y",
            "magnitude": 18.3766,
            "magnitude_error": 0.0049,
            "magnitude_error_upper": null,
            "magnitude_error_lower": null,
            "telescope": "PS1",
            "epoch": null,
            "comments": null,
            "reference": "Cham16",
            "regime": "optical"
        },
        {
            "band": "PAN-STARRS/PS1.z",
            "magnitude": 19.3051,
            "magnitude_error": 0.0158,
            "magnitude_error_upper": null,
            "magnitude_error_lower": null,
            "telescope": "PS1",
            "epoch": null,
            "comments": null,
            "reference": "Cham16",
            "regime": "optical"
        },
        {
            "band": "UKIRT/WFCAM.Y",
            "magnitude": 17.58,
            "magnitude_error": 0.018,
            "magnitude_error_upper": null,
            "magnitude_error_lower": null,
            "telescope": null,
            "epoch": null,
            "comments": null,
            "reference": "WFAU19",
            "regime": "nir"
        },
        {
            "band": "WISE/WISE.W1",
            "magnitude": 15.332,
            "magnitude_error": 0.02,
            "magnitude_error_upper": null,
            "magnitude_error_lower": null,
            "telescope": "WISE",
            "epoch": null,
            "comments": null,
            "reference": "Maro21",
            "regime": "infrared"
        },
        {
            "band": "WISE/WISE.W2",
            "magnitude": 14.991,
            "magnitude_error": 0.031,
            "magnitude_error_upper": null,
            "magnitude_error_lower": null,
            "telescope": "WISE",
            "epoch": null,
            "comments": null,
            "reference": "Maro21",
            "regime": "infrared"
        },
        {
            "band": "WISE/WISE.W3",
            "magnitude": 12.491,
            "magnitude_error": null,
            "magnitude_error_upper": null,
            "magnitude_error_lower": null,
            "telescope": "WISE",
            "epoch": null,
            "comments": "upper limit",
            "reference": "Cutr13",
            "regime": "infrared"
        },
        {
            "band": "WISE/WISE.W4",
            "magnitude": 8.879,
            "magnitude_error": null,
            "magnitude_error_upper": null,
            "magnitude_error_lower": null,
            "telescope": "WISE",
            "epoch": null,
            "comments": "upper limit",
            "reference": "Cutr13",
            "regime": "infrared"
        }
    ],
    "Positions": [
        {
            "ra_deg": 191.295241,
            "dec_deg": -1.541921,
            "epoch_year": 2000.0,
            "reference": "Abaz09"
        },
        {
            "ra_deg": 191.295277,
            "dec_deg": -1.542006,
            "epoch_year": 2000.2600958247776,
            "reference": "Cutr03"
        },
        {
            "ra_deg": 191.2947693,
            "dec_deg": -1.541757,
            "epoch_year": 2016.0,
            "reference": "Gaia23"
        },
        {
            "ra_deg": 191.2949,
            "dec_deg": -1.5418,
            "epoch_year": 2011.962135523614,
            "reference": "Magn20"
        },
        {
            "ra_deg": 191.2947583,
            "dec_deg": -1.5417807,
            "epoch_year": 2015.405,
            "reference": "Maro21"
        }
    ],
    "ProperMotions": [
        {
            "pm_ra": -112.8,
            "pm_ra_error": 6.0,
            "pm_ra_error_upper": null,
            "pm_ra_error_lower": null,
            "pm_dec": 46.7,
            "pm_dec_error": 5.7,
            "pm_dec_error_upper": null,
            "pm_dec_error_lower": null,
            "adopted": true,
            "comments": null,
            "reference": "Best18"
        },
        {
            "pm_ra": -108.8,
            "pm_ra_error": 8.21,
            "pm_ra_error_upper": null,
            "pm_ra_error_lower": null,
            "pm_dec": 42.74,
            "pm_dec_error": 8.06,
            "pm_dec_error_upper": null,
            "pm_dec_error_lower": null,
            "adopted": false,
            "comments": null,
            "reference": "Magn20"
        },
        {
            "pm_ra": -89.0,
            "pm_ra_error": 18.1,
            "pm_ra_error_upper": null,
            "pm_ra_error_lower": null,
            "pm_dec": 17.7,
            "pm_dec_error": 20.3,
            "pm_dec_error_upper": null,
            "pm_dec_error_lower": null,
            "adopted": false,
            "comments": null,
            "reference": "Maro21"
        }
    ],
    "RadialVelocities": [
        {
            "rv_kms": -48.0,
            "rv_error": 51.0,
            "rv_error_upper": null,
            "rv_error_lower": null,
            "adopted": false,
            "comments": null,
            "reference": "Abaz09"
        }
    ],
    "SourceTypes": [
        {
            "source_type": "L0",
            "comments": "optical spectral type",
            "adopted": null,
            "reference": "Schm10b"
        }
    ]
}