{
    "Sources": [
        {
            "source": "SDSS J163748.65+275254.6",
            "ra_deg": 249.4529,
            "dec_deg": 27.8819,
            "epoch_year": 2000.0,
            "equinox": "J2000",
            "reference": "Zhan10",
            "other_references": null,
            "comments": null
        }
    ],
    "ModeledParameters": [
        {
            "model": "UCS adopted distance",
            "parameter": "distance",
            "value": 50.5,
            "error": 0.8,
            "error_upper": null,
            "error_lower": null,
            "unit": "pc",
            "comments": "distance source: dist_plx_formula",
            "reference": "UCS_24"
        },
        {
            "model": "UCS age assignment",
            "parameter": "age",
            "value": 2.5,
            "error": null,
            "error_upper": null,
            "error_lower": null,
            "unit": "Gyr",
            "comments": "age_category: Field; age range (Gyr): 2.5(+4.3/-2)",
            "reference": "UCS_24"
        }
    ],
    "Names": [
        {
            "other_name": "SDSS J163748.65+275254.6"
        }
    ],
    "Parallaxes": [
        {
            "parallax_mas": 19.7761,
            "parallax_error": 0.3166,
            "parallax_error_upper": null,
            "parallax_error_lower": null,
            "adopted": false,
            "comments": null,
            "reference": "Gaia21a"
        },
        {
            "parallax_mas": 19.7761,
            "parallax_error": 0.3166,
            "parallax_error_upper": null,
            "parallax_error_lower": null,
            "adopted": true,
            "comments": null,
            "reference": "Gaia23"
        }
    ],
    "Photometry": [
        {
            "band": "2MASS/2MASS.H",
            "magnitude": 14.156,
            "magnitude_error": 0.053,
            "magnitude_error_upper": null,
            "magnitude_error_lower": null,
            "telescope": "2MASS",
            "epoch": null,
            "comments": null,
            "reference": "Cutr03",
            "regime": "nir"
        },
        {
            "band": "2MASS/2MASS.J",
            "magnitude": 14.947,
            "magnitude_error": 0.038,
            "magnitude_error_upper": null,
            "magnitude_error_lower": null,
            "telescope": "2MASS",
            "epoch": null,
            "comments": null,
            "reference": "Cutr03",
            "regime": "nir"
        },
        {
            "band": "2MASS/2MASS.Ks",
            "magnitude": 13.844,
            "magnitude_error": 0.053,
            "magnitude_error_upper": null,
            "magnitude_error_lower": null,
            "telescope": "2MASS",
            "epoch": null,
            "comments": null,
            "reference": "Cutr03",
            "regime": "nir"
        },
        {
            "band": "GAIA/GAIA3.G",
            "magnitude": 19.5304,
            "magnitude_error": 0.004,
            "magnitude_error_upper": null,
            "magnitude_error_lower": null,
            "telescope": "Gaia",
            "epoch": null,
            "comments": null,
            "reference": "Gaia23",
            "regime": "optical"
        },
        {
            "band": "GAIA/GAIA3.Gbp",
            "magnitude": 21.3369,
            "magnitude_error": 0.1167,
            "magnitude_error_upper": null,
            "magnitude_error_lower": null,
            "telescope": "Gaia",
            "epoch": null,
            "comments": null,
            "reference": "Gaia23",
            "regime": "optical"
        },
        {
            "band": "GAIA/GAIA3.Grp",
            "magnitude": 17.9311,
            "magnitude_error": 0.0127,
            "magnitude_error_upper": null,
            "magnitude_error_lower": null,
            "telescope": "Gaia",
            "epoch": null,
            "comments": null,
            "reference": "Gaia23",
            "regime": "optical"
        },
        {
            "band": "MKO/NSFCam.H",
            "magnitude": 14.309,
            "magnitude_error": 0.004,
            "magnitude_error_upper": null,
            "magnitude_error_lower": null,
            "telescope": null,
            "epoch": null,
            "comments": null,
            "reference": "Lawr12",
            "regime": "nir"
        },
        {
            "band": "MKO/NSFCam.J",
            "magnitude": 14.897,
            "magnitude_error": 0.003,
            "magnitude_error_upper": null,
            "magnitude_error_lower": null,
            "telescope": null,
            "epoch": null,
            "comments": null,
            "reference": "WFAU19",
            "regime": "nir"
        },
        {
            "band": "MKO/NSFCam.K",
            "magnitude": 13.796,
            "magnitude_error": 0.005,
            "magnitude_error_upper": null,
            "magnitude_error_lower": null,
            "telescope": null,
            "epoch": null,
            "comments": null,
            "reference": "Lawr12",
            "regime": "nir"
        },
        {
            "band": "PAN-STARRS/PS1.i",
            "magnitude": 19.041,
            "magnitude_error": 0.0093,
            "magnitude_error_upper": null,
            "magnitude_error_lower": null,
            "telescope": "PS1",
            "epoch": null,
            "comments": null,
            "reference": "Cham16",
            "regime": "optical"
        },
        {
            "band": "PAN-STARRS/PS1.r",
            "magnitude": 21.4308,
            "magnitude_error": 0.0338,
            "magnitude_error_upper": null,
            "magnitude_error_lower": null,
            "telescope": "PS1",
            "epoch": null,
            "comments": null,
            "reference": "Cham16",
            "regime": "optical"
        },
        {
            "band": "PAN-STARRS/PS1.y",
            "magnitude": 16.706,
            "magnitude_error": 0.0059,
            "magnitude_error_upper": null,
            "magnitude_error_lower": null,
            "telescope": "PS1",
            "epoch": null,
            "comments": null,
            "reference": "Cham16",
            "regime": "optical"
        },
        {
            "band": "PAN-STARRS/PS1.z",
            "magnitude": 17.5946,
            "magnitude_error": 0.0074,
            "magnitude_error_upper": null,
            "magnitude_error_lower": null,
            "telescope": "PS1",
            "epoch": null,
            "comments": null,
            "reference": "Cham16",
            "regime": "optical"
        },
        {
            "band": "UKIRT/WFCAM.Y",
            "magnitude": 15.834,
            "magnitude_error": 0.006,
            "magnitude_error_upper": null,
            "magnitude_error_lower": null,
            "telescope": null,
            "epoch": null,
            "comments": null,
            "reference": "Lawr12",
            "regime": "nir"
        },
        {
            "band": "WISE/WISE.W1",
            "magnitude": 13.517,
            "magnitude_error": 0.012,
            "magnitude_error_upper": null,
            "magnitude_error_lower": null,
            "telescope": "WISE",
            "epoch": null,
            "comments": null,
            "reference": "Maro21",
            "regime": "infrared"
        },
        {
            "band": "WISE/WISE.W2",
            "magnitude": 13.263,
            "magnitude_error": 0.01,
            "magnitude_error_upper": null,
            "magnitude_error_lower": null,
            "telescope": "WISE",
            "epoch": null,
            "comments": null,
            "reference": "Maro21",
            "regime": "infrared"
        },
        {
            "band": "WISE/WISE.W3",
            "magnitude": 12.655,
            "magnitude_error": 0.438,
            "magnitude_error_upper": null,
            "magnitude_error_lower": null,
            "telescope": "WISE",
            "epoch": null,
            "comments": null,
            "reference": "Cutr13",
            "regime": "infrared"
        },
        {
            "band": "WISE/WISE.W4",
            "magnitude": 9.208,
            "magnitude_error": null,
            "magnitude_error_upper": null,
            "magnitude_error_lower": null,
            "telescope": "WISE",
            "epoch": null,
            "comments": "upper limit",
            "reference": "Cutr13",
            "regime": "infrared"
        }
    ],
    "Positions": [
        {
            "ra_deg": 249.452949,
            "dec_deg": 27.881962,
            "epoch_year": 2000.1560574948664,
            "reference": "Cutr03"
        },
        {
            "ra_deg": 249.452946,
            "dec_deg": 27.8819259,
            "epoch_year": 2000.0,
            "reference": "Gaia21a"
        },
        {
            "ra_deg": 249.4519653,
            "dec_deg": 27.8815689,
            "epoch_year": 2016.0,
            "reference": "Gaia23"
        },
        {
            "ra_deg": 249.4522,
            "dec_deg": 27.8817,
            "epoch_year": 2011.5931279945244,
            "reference": "Magn20"
        },
        {
            "ra_deg": 249.4520069,
            "dec_deg": 27.8815985,
            "epoch_year": 2015.405,
            "reference": "Maro21"
        }
    ],
    "ProperMotions": [
        {
            "pm_ra": -193.2,
            "pm_ra_error": 2.0,
            "pm_ra_error_upper": null,
            "pm_ra_error_lower": null,
            "pm_dec": -76.7,
            "pm_dec_error": 2.3,
            "pm_dec_error_upper": null,
            "pm_dec_error_lower": null,
            "adopted": false,
            "comments": null,
            "reference": "Best18"
        },
        {
            "pm_ra": -193.785,
            "pm_ra_error": 0.31,
            "pm_ra_error_upper": null,
            "pm_ra_error_lower": null,
            "pm_dec": -80.454,
            "pm_dec_error": 0.312,
            "pm_dec_error_upper": null,
            "pm_dec_error_lower": null,
            "adopted": false,
            "comments": null,
            "reference": "Gaia21a"
        },
        {
            "pm_ra": -193.785,
            "pm_ra_error": 0.31,
            "pm_ra_error_upper": null,
            "pm_ra_error_lower": null,
            "pm_dec": -80.454,
            "pm_dec_error": 0.312,
            "pm_dec_error_upper": null,
            "pm_dec_error_lower": null,
            "adopted": true,
            "comments": null,
            "reference": "Gaia23"
        },
        {
            "pm_ra": -194.83,
            "pm_ra_error": 3.74,
            "pm_ra_error_upper": null,
            "pm_ra_error_lower": null,
            "pm_dec": -78.05,
            "pm_dec_error": 3.37,
            "pm_dec_error_upper": null,
            "pm_dec_error_lower": null,
            "adopted": false,
            "comments": null,
            "reference": "Magn20"
        },
        {
            "pm_ra": -206.1,
            "pm_ra_error": 5.3,
            "pm_ra_error_upper": null,
            "pm_ra_error_lower": null,
            "pm_dec": -97.0,
            "pm_dec_error": 5.9,
            "pm_dec_error_upper": null,
            "pm_dec_error_lower": null,
            "adopted": false,
            "comments": null,
            "reference": "Maro21"
        },
        {
            "pm_ra": -226.0,
            "pm_ra_error": 13.0,
            "pm_ra_error_upper": null,
            "pm_ra_error_lower": null,
            "pm_dec": -86.0,
            "pm_dec_error": 13.0,
            "pm_dec_error_upper": null,
            "pm_dec_error_lower": null,
            "adopted": false,
            "comments": null,
            "reference": "Zhan10"
        }
    ],
    "RadialVelocities": [
        {
            "rv_kms": -75.0,
            "rv_error": null,
            "rv_error_upper": null,
            "rv_error_lower": null,
            "adopted": true,
            "comments": null,
            "reference": "West11"
        }
    ],
    "SourceTypes": [
        {
            "source_type": "L0",
            "comments": "optical spectral type",
            "adopted": null,
            "reference": "Zhan10"
        }
    ]
}