{
    "Sources": [
        {
            "source": "SDSS J091524.34+383128.3",
            "ra_deg": 138.8514,
            "dec_deg": 38.5245,
            "epoch_year": 2000.0,
            "equinox": "J2000",
            "reference": "West08",
            "other_references": null,
            "comments": null
        }
    ],
    "ModeledParameters": [
        {
            "model": "UCS adopted distance",
            "parameter": "distance",
            "value": 98.0,
            "error": 17.0,
            "error_upper": null,
            "error_lower": null,
            "unit": "pc",
            "comments": "distance source: dist_plx_formula",
            "reference": "UCS_24"
        },
        {
            "model": "UCS age assignment",
            "parameter": "age",
            "value": 2.5,
            "error": null,
            "error_upper": null,
            "error_lower": null,
            "unit": "Gyr",
            "comments": "age_category: Field; age range (Gyr): 2.5(+4.3/-2)",
            "reference": "UCS_24"
        }
    ],
    "Names": [
        {
            "other_name": "SDSS J091524.34+383128.3"
        }
    ],
    "Parallaxes": [
        {
            "parallax_mas": 10.1827,
            "parallax_error": 1.7831,
            "parallax_error_upper": null,
            "parallax_error_lower": null,
            "adopted": false,
            "comments": null,
            "reference": "Gaia21a"
        },
        {
            "parallax_mas": 10.1827,
            "parallax_error": 1.7831,
            "parallax_error_upper": null,
            "parallax_error_lower": null,
            "adopted": true,
            "comments": null,
            "reference": "Gaia23"
        }
    ],
    "Photometry": [
        {
            "band": "2MASS/2MASS.H",
            "magnitude": 15.316,
            "magnitude_error": 0.113,
            "magnitude_error_upper": null,
            "magnitude_error_lower": null,
            "telescope": "2MASS",
            "epoch": null,
            "comments": null,
            "reference": "Cutr03",
            "regime": "nir"
        },
        {
            "band": "2MASS/2MASS.J",
            "magnitude": 16.243,
            "magnitude_error": 0.108,
            "magnitude_error_upper": null,
            "magnitude_error_lower": null,
            "telescope": "2MASS",
            "epoch": null,
            "comments": null,
            "reference": "Cutr03",
            "regime": "nir"
        },
        {
            "band": "2MASS/2MASS.Ks",
            "magnitude": 14.735,
            "magnitude_error": 0.113,
            "magnitude_error_upper": null,
            "magnitude_error_lower": null,
            "telescope": "2MASS",
            "epoch": null,
            "comments": null,
            "reference": "Cutr03",
            "regime": "nir"
        },
        {
            "band": "GAIA/GAIA3.G",
            "magnitude": 20.9151,
            "magnitude_error": 0.0125,
            "magnitude_error_upper": null,
            "magnitude_error_lower": null,
            "telescope": "Gaia",
            "epoch": null,
            "comments": null,
            "reference": "Gaia23",
            "regime": "optical"
        },
        {
            "band": "GAIA/GAIA3.Gbp",
            "magnitude": 21.1325,
            "magnitude_error": 0.3259,
            "magnitude_error_upper": null,
            "magnitude_error_lower": null,
            "telescope": "Gaia",
            "epoch": null,
            "comments": null,
            "reference": "Gaia23",
            "regime": "optical"
        },
        {
            "band": "GAIA/GAIA3.Grp",
            "magnitude": 19.2351,
            "magnitude_error": 0.0763,
            "magnitude_error_upper": null,
            "magnitude_error_lower": null,
            "telescope": "Gaia",
            "epoch": null,
            "comments": null,
            "reference": "Gaia23",
            "regime": "optical"
        },
        {
            "band": "MKO/NSFCam.J",
            "magnitude": 16.007,
            "magnitude_error": 0.012,
            "magnitude_error_upper": null,
            "magnitude_error_lower": null,
            "telescope": null,
            "epoch": null,
            "comments": null,
            "reference": "Schn23b",
            "regime": "nir"
        },
        {
            "band": "MKO/NSFCam.K",
            "magnitude": 14.754,
            "magnitude_error": 0.009,
            "magnitude_error_upper": null,
            "magnitude_error_lower": null,
            "telescope": null,
            "epoch": null,
            "comments": null,
            "reference": "Schn23b",
            "regime": "nir"
        },
        {
            "band": "PAN-STARRS/PS1.i",
            "magnitude": 20.4042,
            "magnitude_error": 0.0247,
            "magnitude_error_upper": null,
            "magnitude_error_lower": null,
            "telescope": "PS1",
            "epoch": null,
            "comments": null,
            "reference": "Cham16",
            "regime": "optical"
        },
        {
            "band": "PAN-STARRS/PS1.r",
            "magnitude": 22.7006,
            "magnitude_error": 0.0617,
            "magnitude_error_upper": null,
            "magnitude_error_lower": null,
            "telescope": "PS1",
            "epoch": null,
            "comments": null,
            "reference": "Cham16",
            "regime": "optical"
        },
        {
            "band": "PAN-STARRS/PS1.y",
            "magnitude": 17.9555,
            "magnitude_error": 0.0075,
            "magnitude_error_upper": null,
            "magnitude_error_lower": null,
            "telescope": "PS1",
            "epoch": null,
            "comments": null,
            "reference": "Cham16",
            "regime": "optical"
        },
        {
            "band": "PAN-STARRS/PS1.z",
            "magnitude": 18.8962,
            "magnitude_error": 0.01,
            "magnitude_error_upper": null,
            "magnitude_error_lower": null,
            "telescope": "PS1",
            "epoch": null,
            "comments": null,
            "reference": "Cham16",
            "regime": "optical"
        },
        {
            "band": "WISE/WISE.W1",
            "magnitude": 14.483,
            "magnitude_error": 0.015,
            "magnitude_error_upper": null,
            "magnitude_error_lower": null,
            "telescope": "WISE",
            "epoch": null,
            "comments": null,
            "reference": "Maro21",
            "regime": "infrared"
        },
        {
            "band": "WISE/WISE.W2",
            "magnitude": 14.238,
            "magnitude_error": 0.017,
            "magnitude_error_upper": null,
            "magnitude_error_lower": null,
            "telescope": "WISE",
            "epoch": null,
            "comments": null,
            "reference": "Maro21",
            "regime": "infrared"
        },
        {
            "band": "WISE/WISE.W3",
            "magnitude": 12.704,
            "magnitude_error": null,
            "magnitude_error_upper": null,
            "magnitude_error_lower": null,
            "telescope": "WISE",
            "epoch": null,
            "comments": "upper limit",
            "reference": "Cutr13",
            "regime": "infrared"
        },
        {
            "band": "WISE/WISE.W4",
            "magnitude": 8.769,
            "magnitude_error": null,
            "magnitude_error_upper": null,
            "magnitude_error_lower": null,
            "telescope": "WISE",
            "epoch": null,
            "comments": "upper limit",
            "reference": "Cutr13",
            "regime": "infrared"
        }
    ],
    "Positions": [
        {
            "ra_deg": 138.851527,
            "dec_deg": 38.52459,
            "epoch_year": 1998.2737850787132,
            "reference": "Cutr03"
        },
        {
            "ra_deg": 138.8514422,
            "dec_deg": 38.5245486,
            "epoch_year": 2000.0,
            "reference": "Gaia21a"
        },
        {
            "ra_deg": 138.8511047,
            "dec_deg": 38.5244179,
            "epoch_year": 2016.0,
            "reference": "Gaia23"
        },
        {
            "ra_deg": 138.8512,
            "dec_deg": 38.5244,
            "epoch_year": 2011.784668035592,
            "reference": "Magn20"
        },
        {
            "ra_deg": 138.8511647,
            "dec_deg": 38.5244395,
            "epoch_year": 2015.405,
            "reference": "Maro21"
        }
    ],
    "ProperMotions": [
        {
            "pm_ra": -65.3,
            "pm_ra_error": 2.9,
            "pm_ra_error_upper": null,
            "pm_ra_error_lower": null,
            "pm_dec": -22.9,
            "pm_dec_error": 3.4,
            "pm_dec_error_upper": null,
            "pm_dec_error_lower": null,
            "adopted": false,
            "comments": null,
            "reference": "Best18"
        },
        {
            "pm_ra": -58.964,
            "pm_ra_error": 2.328,
            "pm_ra_error_upper": null,
            "pm_ra_error_lower": null,
            "pm_dec": -29.12,
            "pm_dec_error": 2.126,
            "pm_dec_error_upper": null,
            "pm_dec_error_lower": null,
            "adopted": false,
            "comments": null,
            "reference": "Gaia21a"
        },
        {
            "pm_ra": -58.964,
            "pm_ra_error": 2.328,
            "pm_ra_error_upper": null,
            "pm_ra_error_lower": null,
            "pm_dec": -29.12,
            "pm_dec_error": 2.126,
            "pm_dec_error_upper": null,
            "pm_dec_error_lower": null,
            "adopted": true,
            "comments": null,
            "reference": "Gaia23"
        },
        {
            "pm_ra": -64.18,
            "pm_ra_error": 3.44,
            "pm_ra_error_upper": null,
            "pm_ra_error_lower": null,
            "pm_dec": -22.01,
            "pm_dec_error": 3.47,
            "pm_dec_error_upper": null,
            "pm_dec_error_lower": null,
            "adopted": false,
            "comments": null,
            "reference": "Magn20"
        },
        {
            "pm_ra": -42.6,
            "pm_ra_error": 8.7,
            "pm_ra_error_upper": null,
            "pm_ra_error_lower": null,
            "pm_dec": -14.8,
            "pm_dec_error": 10.0,
            "pm_dec_error_upper": null,
            "pm_dec_error_lower": null,
            "adopted": false,
            "comments": null,
            "reference": "Maro21"
        }
    ],
    "RadialVelocities": [
        {
            "rv_kms": 0.0,
            "rv_error": 57.0,
            "rv_error_upper": null,
            "rv_error_lower": null,
            "adopted": false,
            "comments": null,
            "reference": "Abaz09"
        }
    ],
    "SourceTypes": [
        {
            "source_type": "L0",
            "comments": "optical spectral type",
            "adopted": null,
            "reference": "West08"
        }
    ]
}