{
    "Sources": [
        {
            "source": "SDSS J154951.39+490450.1",
            "ra_deg": 237.4641,
            "dec_deg": 49.0806,
            "epoch_year": 2000.0,
            "equinox": "J2000",
            "reference": "West08",
            "other_references": null,
            "comments": null
        }
    ],
    "ModeledParameters": [
        {
            "model": "UCS adopted distance",
            "parameter": "distance",
            "value": 84.0,
            "error": 6.0,
            "error_upper": null,
            "error_lower": null,
            "unit": "pc",
            "comments": "distance source: dist_W2_formula",
            "reference": "UCS_24"
        },
        {
            "model": "UCS age assignment",
            "parameter": "age",
            "value": 2.5,
            "error": null,
            "error_upper": null,
            "error_lower": null,
            "unit": "Gyr",
            "comments": "age_category: Field; age range (Gyr): 2.5(+4.3/-2)",
            "reference": "UCS_24"
        }
    ],
    "Names": [
        {
            "other_name": "SDSS J154951.39+490450.1"
        }
    ],
    "Photometry": [
        {
            "band": "2MASS/2MASS.H",
            "magnitude": 15.317,
            "magnitude_error": 0.159,
            "magnitude_error_upper": null,
            "magnitude_error_lower": null,
            "telescope": "2MASS",
            "epoch": null,
            "comments": null,
            "reference": "Cutr03",
            "regime": "nir"
        },
        {
            "band": "2MASS/2MASS.J",
            "magnitude": 16.245,
            "magnitude_error": 0.097,
            "magnitude_error_upper": null,
            "magnitude_error_lower": null,
            "telescope": "2MASS",
            "epoch": null,
            "comments": null,
            "reference": "Cutr03",
            "regime": "nir"
        },
        {
            "band": "2MASS/2MASS.Ks",
            "magnitude": 15.066,
            "magnitude_error": 0.159,
            "magnitude_error_upper": null,
            "magnitude_error_lower": null,
            "telescope": "2MASS",
            "epoch": null,
            "comments": null,
            "reference": "Cutr03",
            "regime": "nir"
        },
        {
            "band": "GAIA/GAIA3.G",
            "magnitude": 21.1822,
            "magnitude_error": 0.0304,
            "magnitude_error_upper": null,
            "magnitude_error_lower": null,
            "telescope": "Gaia",
            "epoch": null,
            "comments": null,
            "reference": "Gaia23",
            "regime": "optical"
        },
        {
            "band": "GAIA/GAIA3.Gbp",
            "magnitude": 21.5529,
            "magnitude_error": 0.2707,
            "magnitude_error_upper": null,
            "magnitude_error_lower": null,
            "telescope": "Gaia",
            "epoch": null,
            "comments": null,
            "reference": "Gaia23",
            "regime": "optical"
        },
        {
            "band": "GAIA/GAIA3.Grp",
            "magnitude": 19.835,
            "magnitude_error": 0.1799,
            "magnitude_error_upper": null,
            "magnitude_error_lower": null,
            "telescope": "Gaia",
            "epoch": null,
            "comments": null,
            "reference": "Gaia23",
            "regime": "optical"
        },
        {
            "band": "MKO/NSFCam.J",
            "magnitude": 16.349,
            "magnitude_error": 0.013,
            "magnitude_error_upper": null,
            "magnitude_error_lower": null,
            "telescope": null,
            "epoch": null,
            "comments": null,
            "reference": "Schn23b",
            "regime": "nir"
        },
        {
            "band": "MKO/NSFCam.K",
            "magnitude": 15.072,
            "magnitude_error": 0.013,
            "magnitude_error_upper": null,
            "magnitude_error_lower": null,
            "telescope": null,
            "epoch": null,
            "comments": null,
            "reference": "Schn23b",
            "regime": "nir"
        },
        {
            "band": "PAN-STARRS/PS1.i",
            "magnitude": 20.7207,
            "magnitude_error": 0.0247,
            "magnitude_error_upper": null,
            "magnitude_error_lower": null,
            "telescope": "PS1",
            "epoch": null,
            "comments": null,
            "reference": "Cham16",
            "regime": "optical"
        },
        {
            "band": "PAN-STARRS/PS1.r",
            "magnitude": 22.799,
            "magnitude_error": 0.0602,
            "magnitude_error_upper": null,
            "magnitude_error_lower": null,
            "telescope": "PS1",
            "epoch": null,
            "comments": null,
            "reference": "Cham16",
            "regime": "optical"
        },
        {
            "band": "PAN-STARRS/PS1.y",
            "magnitude": 18.3018,
            "magnitude_error": 0.0257,
            "magnitude_error_upper": null,
            "magnitude_error_lower": null,
            "telescope": "PS1",
            "epoch": null,
            "comments": null,
            "reference": "Cham16",
            "regime": "optical"
        },
        {
            "band": "PAN-STARRS/PS1.z",
            "magnitude": 19.2428,
            "magnitude_error": 0.0148,
            "magnitude_error_upper": null,
            "magnitude_error_lower": null,
            "telescope": "PS1",
            "epoch": null,
            "comments": null,
            "reference": "Cham16",
            "regime": "optical"
        },
        {
            "band": "WISE/WISE.W1",
            "magnitude": 14.789,
            "magnitude_error": 0.015,
            "magnitude_error_upper": null,
            "magnitude_error_lower": null,
            "telescope": "WISE",
            "epoch": null,
            "comments": null,
            "reference": "Maro21",
            "regime": "infrared"
        },
        {
            "band": "WISE/WISE.W2",
            "magnitude": 14.531,
            "magnitude_error": 0.015,
            "magnitude_error_upper": null,
            "magnitude_error_lower": null,
            "telescope": "WISE",
            "epoch": null,
            "comments": null,
            "reference": "Maro21",
            "regime": "infrared"
        }
    ],
    "Positions": [
        {
            "ra_deg": 237.463943,
            "dec_deg": 49.080612,
            "epoch_year": 2000.3203285420946,
            "reference": "Cutr03"
        },
        {
            "ra_deg": 237.4638336,
            "dec_deg": 49.0807349,
            "epoch_year": 2000.0,
            "reference": "Gaia21a"
        },
        {
            "ra_deg": 237.4638367,
            "dec_deg": 49.0807343,
            "epoch_year": 2016.0,
            "reference": "Gaia23"
        },
        {
            "ra_deg": 237.4639,
            "dec_deg": 49.0807,
            "epoch_year": 2011.9311430527036,
            "reference": "Magn20"
        },
        {
            "ra_deg": 237.4638272,
            "dec_deg": 49.0807115,
            "epoch_year": 2015.405,
            "reference": "Maro21"
        }
    ],
    "ProperMotions": [
        {
            "pm_ra": -30.6,
            "pm_ra_error": 6.1,
            "pm_ra_error_upper": null,
            "pm_ra_error_lower": null,
            "pm_dec": 34.9,
            "pm_dec_error": 6.3,
            "pm_dec_error_upper": null,
            "pm_dec_error_lower": null,
            "adopted": true,
            "comments": null,
            "reference": "Best18"
        },
        {
            "pm_ra": -31.12,
            "pm_ra_error": 6.22,
            "pm_ra_error_upper": null,
            "pm_ra_error_lower": null,
            "pm_dec": 32.56,
            "pm_dec_error": 6.22,
            "pm_dec_error_upper": null,
            "pm_dec_error_lower": null,
            "adopted": false,
            "comments": null,
            "reference": "Magn20"
        },
        {
            "pm_ra": -52.2,
            "pm_ra_error": 7.3,
            "pm_ra_error_upper": null,
            "pm_ra_error_lower": null,
            "pm_dec": 36.4,
            "pm_dec_error": 9.1,
            "pm_dec_error_upper": null,
            "pm_dec_error_lower": null,
            "adopted": false,
            "comments": null,
            "reference": "Maro21"
        }
    ],
    "RadialVelocities": [
        {
            "rv_kms": -99.0,
            "rv_error": 54.0,
            "rv_error_upper": null,
            "rv_error_lower": null,
            "adopted": false,
            "comments": null,
            "reference": "Abaz09"
        }
    ],
    "SourceTypes": [
        {
            "source_type": "L0",
            "comments": "optical spectral type",
            "adopted": null,
            "reference": "West08"
        }
    ]
}