{
    "Sources": [
        {
            "source": "WISEA J235402.79+024014.1",
            "ra_deg": 358.5103,
            "dec_deg": 2.6722,
            "epoch_year": 2000.0,
            "equinox": "J2000",
            "reference": "Schn15",
            "other_references": null,
            "comments": null
        }
    ],
    "ModeledParameters": [
        {
            "model": "UCS adopted distance",
            "parameter": "distance",
            "value": 7.63,
            "error": 0.17,
            "error_upper": null,
            "error_lower": null,
            "unit": "pc",
            "comments": "distance source: dist_plx_formula",
            "reference": "UCS_24"
        },
        {
            "model": "UCS age assignment",
            "parameter": "age",
            "value": 2.5,
            "error": null,
            "error_upper": null,
            "error_lower": null,
            "unit": "Gyr",
            "comments": "age_category: Field; age range (Gyr): 2.5(+4.3/-2)",
            "reference": "UCS_24"
        }
    ],
    "Names": [
        {
            "other_name": "WISEA J235402.79+024014.1"
        }
    ],
    "Parallaxes": [
        {
            "parallax_mas": 124.1,
            "parallax_error": 4.9,
            "parallax_error_upper": null,
            "parallax_error_lower": null,
            "adopted": false,
            "comments": null,
            "reference": "Kirk19"
        },
        {
            "parallax_mas": 130.6,
            "parallax_error": 3.3,
            "parallax_error_upper": null,
            "parallax_error_lower": null,
            "adopted": true,
            "comments": null,
            "reference": "Kirk21"
        }
    ],
    "Photometry": [
        {
            "band": "MKO/NSFCam.H",
            "magnitude": 22.882,
            "magnitude_error": 0.3,
            "magnitude_error_upper": null,
            "magnitude_error_lower": null,
            "telescope": null,
            "epoch": null,
            "comments": null,
            "reference": "Schn15",
            "regime": "nir"
        },
        {
            "band": "MKO/NSFCam.J",
            "magnitude": 23.068,
            "magnitude_error": 0.199,
            "magnitude_error_upper": null,
            "magnitude_error_lower": null,
            "telescope": null,
            "epoch": null,
            "comments": null,
            "reference": "Schn15",
            "regime": "nir"
        },
        {
            "band": "Spitzer/IRAC.I1",
            "magnitude": 18.11,
            "magnitude_error": 0.11,
            "magnitude_error_upper": null,
            "magnitude_error_lower": null,
            "telescope": "Spitzer",
            "epoch": null,
            "comments": null,
            "reference": "Schn15",
            "regime": "infrared"
        },
        {
            "band": "Spitzer/IRAC.I2",
            "magnitude": 15.01,
            "magnitude_error": 0.02,
            "magnitude_error_upper": null,
            "magnitude_error_lower": null,
            "telescope": "Spitzer",
            "epoch": null,
            "comments": null,
            "reference": "Schn15",
            "regime": "infrared"
        },
        {
            "band": "WISE/WISE.W1",
            "magnitude": 18.053,
            "magnitude_error": 0.142,
            "magnitude_error_upper": null,
            "magnitude_error_lower": null,
            "telescope": "WISE",
            "epoch": null,
            "comments": null,
            "reference": "Maro21",
            "regime": "infrared"
        },
        {
            "band": "WISE/WISE.W2",
            "magnitude": 15.018,
            "magnitude_error": 0.03,
            "magnitude_error_upper": null,
            "magnitude_error_lower": null,
            "telescope": "WISE",
            "epoch": null,
            "comments": null,
            "reference": "Maro21",
            "regime": "infrared"
        },
        {
            "band": "WISE/WISE.W3",
            "magnitude": 12.278,
            "magnitude_error": null,
            "magnitude_error_upper": null,
            "magnitude_error_lower": null,
            "telescope": "WISE",
            "epoch": null,
            "comments": "upper limit",
            "reference": "Cutr13",
            "regime": "infrared"
        },
        {
            "band": "WISE/WISE.W4",
            "magnitude": 8.949,
            "magnitude_error": null,
            "magnitude_error_upper": null,
            "magnitude_error_lower": null,
            "telescope": "WISE",
            "epoch": null,
            "comments": "upper limit",
            "reference": "Cutr13",
            "regime": "infrared"
        }
    ],
    "Positions": [
        {
            "ra_deg": 358.5122297,
            "dec_deg": 2.67017,
            "epoch_year": 2015.405,
            "reference": "Maro21"
        },
        {
            "ra_deg": 358.51162,
            "dec_deg": 2.67058,
            "epoch_year": 2000.0,
            "reference": "Schn15"
        }
    ],
    "ProperMotions": [
        {
            "pm_ra": 491.1,
            "pm_ra_error": 2.8,
            "pm_ra_error_upper": null,
            "pm_ra_error_lower": null,
            "pm_dec": -393.1,
            "pm_dec_error": 3.0,
            "pm_dec_error_upper": null,
            "pm_dec_error_lower": null,
            "adopted": false,
            "comments": null,
            "reference": "Kirk19"
        },
        {
            "pm_ra": 503.5,
            "pm_ra_error": 2.2,
            "pm_ra_error_upper": null,
            "pm_ra_error_lower": null,
            "pm_dec": -399.5,
            "pm_dec_error": 2.3,
            "pm_dec_error_upper": null,
            "pm_dec_error_lower": null,
            "adopted": true,
            "comments": null,
            "reference": "Kirk21"
        },
        {
            "pm_ra": 449.2,
            "pm_ra_error": 38.1,
            "pm_ra_error_upper": null,
            "pm_ra_error_lower": null,
            "pm_dec": -474.2,
            "pm_dec_error": 38.9,
            "pm_dec_error_upper": null,
            "pm_dec_error_lower": null,
            "adopted": false,
            "comments": null,
            "reference": "Maro21"
        }
    ],
    "SourceTypes": [
        {
            "source_type": "Y1",
            "comments": "NIR spectral type",
            "adopted": null,
            "reference": "Schn15"
        }
    ]
}